setup.cfg
setup.py
src/django_token_auth.egg-info/PKG-INFO
src/django_token_auth.egg-info/SOURCES.txt
src/django_token_auth.egg-info/dependency_links.txt
src/django_token_auth.egg-info/requires.txt
src/django_token_auth.egg-info/top_level.txt
src/token_auth/__init__.py
src/token_auth/admin.py
src/token_auth/development_settings.py
src/token_auth/forms.py
src/token_auth/manage.py
src/token_auth/managers.py
src/token_auth/middleware.py
src/token_auth/models.py
src/token_auth/settings.py
src/token_auth/signals.py
src/token_auth/test_settings.py
src/token_auth/urls.py
src/token_auth/views.py
src/token_auth/tests/__init__.py
src/token_auth/tests/urls.py
src/token_auth/tests/views.py