Metadata-Version: 1.0
Name: django-token-auth
Version: 0.3.2b2
Summary: app that provides limited authentication via hash-type URL.
Home-page: http://github.com/mogga/django-token-auth/
Author: Oyvind Saltvik, Robert Moggach
Author-email: oyvind.saltvik@gmail.com, rob@moggach.com
License: BSD
Keywords: python django hash authentication
Platform: UNKNOWN
Classifier: Development Status :: 4 - Beta
Classifier: Programming Language :: Python
Classifier: Framework :: Django
Classifier: Intended Audience :: Developers
Classifier: Operating System :: OS Independent
Classifier: License :: OSI Approved :: BSD License
Classifier: Topic :: Internet :: WWW/HTTP
